kiwoom_api/__init__.py
kiwoom_api/api/__init__.py
kiwoom_api/api/_config.py
kiwoom_api/api/_errors.py
kiwoom_api/api/_logger.py
kiwoom_api/api/data_feeder.py
kiwoom_api/api/errors.py
kiwoom_api/api/executor.py
kiwoom_api/api/kiwoom.py
kiwoom_api/api/return_codes.py
kiwoom_api/config/__init__.py
kiwoom_api/config/api.py
kiwoom_api/config/db.py
kiwoom_api/utility/__init__.py
kiwoom_api/utility/_tick_calculator.py
kiwoom_api/utility/utility.py
test/__init__.py
test/data_receive.py
test/send_order.py
test/test.py
test/test_data_feeder.py
test/test_kiwoom.py
kiwoom_api_handler-1.0.11.dist-info/METADATA
kiwoom_api_handler-1.0.11.dist-info/WHEEL
kiwoom_api_handler-1.0.11.dist-info/top_level.txt
kiwoom_api_handler-1.0.11.dist-info/RECORD
