Metadata-Version: 2.1
Name: kiwoom-api-handler
Version: 1.0.11
Summary: a package for hanlding Kiwoom OPEN API+ ActiveX Control with python
Home-page: https://github.com/donghyungko/kiwoom_api_handler.git
Author: Donghyung Ko
Author-email: koko8624@gmail.com
License: MIT
Download-URL: https://github.com/DonghyungKo/kiwoom_api_handler/archive/master.zip
Keywords: Kiwoom,Kiwoom OPEN API+,Kiwoom API,키움증권
Platform: UNKNOWN
Classifier: Programming Language :: Python :: 3.6
Classifier: Programming Language :: Python :: 3.7
Requires-Python: >=3.6
Requires-Dist: pandas (==0.25.1)
Requires-Dist: PyQt5 (==5.14.1)
